easyrag/__init__.py
easyrag/models.py
easyrag/utils.py
easyrag_python-1.0.1.dist-info/LICENSE
easyrag_python-1.0.1.dist-info/METADATA
easyrag_python-1.0.1.dist-info/WHEEL
easyrag_python-1.0.1.dist-info/top_level.txt
easyrag_python-1.0.1.dist-info/RECORD
