Metadata-Version: 2.1
Name: easyrag-python
Version: 1.0.1
Summary: EasyRAG Python Package
Author: Sayed Shaun
Requires-Python: >=3.8
License-File: LICENSE
Requires-Dist: langchain
Requires-Dist: langchain-community
Requires-Dist: langchain-google-genai
Requires-Dist: pypdf
Requires-Dist: torch
Requires-Dist: transformers
Requires-Dist: faiss-cpu
Requires-Dist: sentence-transformers
Requires-Dist: bitsandbytes
Requires-Dist: accelerate
Requires-Dist: youtube-transcript-api
Requires-Dist: pytube
